py/pycrypt.py
pycrypt_dev-0.1.dev1.dist-info/METADATA
pycrypt_dev-0.1.dev1.dist-info/WHEEL
pycrypt_dev-0.1.dev1.dist-info/entry_points.txt
pycrypt_dev-0.1.dev1.dist-info/top_level.txt
pycrypt_dev-0.1.dev1.dist-info/RECORD
