Metadata-Version: 2.1
Name: pycrypt-dev
Version: 0.1.dev1
Summary: A Python packege for Cryptographic algorithms
Home-page: https://github.com/ayanbag/pycrypt
Author: Ayan Bag
Author-email: ayanbag9474@gmail.com
License: MIT
Platform: UNKNOWN
Classifier: Programming Language :: Python :: 3.6
Classifier: License :: OSI Approved :: MIT License
Requires-Python: >=3.4
Requires-Dist: pyperclip
